pollination/dragonfly_energy/__init__.py
pollination/dragonfly_energy/edit.py
pollination/dragonfly_energy/translate.py
pollination_dragonfly_energy-0.2.8.dist-info/LICENSE
pollination_dragonfly_energy-0.2.8.dist-info/METADATA
pollination_dragonfly_energy-0.2.8.dist-info/WHEEL
pollination_dragonfly_energy-0.2.8.dist-info/top_level.txt
pollination_dragonfly_energy-0.2.8.dist-info/RECORD
