Metadata-Version: 2.1
Name: pollination-dragonfly-energy
Version: 0.2.8
Summary: Dragonfly energy plugin for Pollination.
Home-page: https://github.com/pollination/dragonfly-energy
Author: ladybug-tools
Author-email: info@ladybug.tools
Maintainer: chris, ladybug-tools
Maintainer-email: chris@ladybug.tools, info@ladybug.tools
License: PolyForm Shield License 1.0.0, https://polyformproject.org/wp-content/uploads/2020/06/PolyForm-Shield-1.0.0.txt
Project-URL: icon, https://raw.githubusercontent.com/ladybug-tools/artwork/master/icons_bugs/grasshopper_tabs/Dragonfly.png
Project-URL: docker, https://hub.docker.com/r/ladybugtools/dragonfly-energy
Keywords: dragonfly,energy,ladybug-tools,energyplus,openstudio
License-File: LICENSE
Requires-Dist: pollination-dsl (>=0.15.0)
Requires-Dist: dragonfly-energy (>=1.23.45)
